mia/__init__.py
mia/main.py
my_mia-0.0.1.dist-info/LICENSE
my_mia-0.0.1.dist-info/METADATA
my_mia-0.0.1.dist-info/WHEEL
my_mia-0.0.1.dist-info/top_level.txt
my_mia-0.0.1.dist-info/RECORD
