Metadata-Version: 2.1
Name: my-mia
Version: 0.0.1
Summary: Building a personal assistant using LangChain, Python, Streamlit and OpenAI LLMs
Author-email: Amisha Muni <notdisclosed@me.com>
License: GNU AFFERO GENERAL PUBLIC LICENSE
Project-URL: Homepage, https://github.com/amishamuni/mia
Keywords: langchain,python3
Classifier: Development Status :: 3 - Alpha
Classifier: Programming Language :: Python :: 3.11
Classifier: License :: OSI Approved :: GNU Affero General Public License v3 or later (AGPLv3+)
Requires-Python: >=3.11
License-File: LICENSE
